transformapy/__init__.py
transformapy/transformapy.py
transformapy-0.0.6.dist-info/METADATA
transformapy-0.0.6.dist-info/WHEEL
transformapy-0.0.6.dist-info/top_level.txt
transformapy-0.0.6.dist-info/RECORD
