Metadata-Version: 2.1
Name: transformapy
Version: 0.0.6
Summary: A Toolkit for Identifying Transformation Product Structures of Emerging Contaminants Using HRMS Data
Home-page: https://github.com/WangRui5/TransformaPy
Author: Wang Rui
Author-email: wtrt7009@gmail.com
License: UNKNOWN
Platform: UNKNOWN
Classifier: Programming Language :: Python :: 3
Classifier: License :: OSI Approved :: MIT License
Classifier: Operating System :: OS Independent
Requires-Python: >=3.6
Requires-Dist: pyhrms (>=0.9.2)
